lutils/.python-version
lutils/README.md
lutils/uv.lock
lutils/cli/__init__.py
lutils/cli/__main__.py
pylutils-0.1.0.dist-info/METADATA
pylutils-0.1.0.dist-info/WHEEL
pylutils-0.1.0.dist-info/entry_points.txt
pylutils-0.1.0.dist-info/licenses/LICENSE
pylutils-0.1.0.dist-info/RECORD
