Metadata-Version: 2.4
Name: pylutils
Version: 0.1.0
Summary: 随便写写
License-File: LICENSE
Requires-Python: >=3.10
Requires-Dist: click>=8.2.1
Requires-Dist: toml>=0.10.2
